<Properties StartupConfiguration="{5711BF35-EE75-6877-2B09-468FB8E99264}|">
  <MonoDevelop.Ide.Workbench ActiveDocument="Assets/Scripts/Player.cs">
    <Files>
      <File FileName="Assets/Scripts/Player.cs" Line="36" Column="39" />
    </Files>
    <Pads>
      <Pad Id="ProjectPad">
        <State name="__root__">
          <Node name="Gierka 2D" expanded="True">
            <Node name="Assets" expanded="True">
              <Node name="Scripts" expanded="True">
                <Node name="Player.cs" selected="True" />
              </Node>
            </Node>
          </Node>
        </State>
      </Pad>
    </Pads>
  </MonoDevelop.Ide.Workbench>
  <MonoDevelop.Ide.DebuggingService.PinnedWatches />
  <MonoDevelop.Ide.Workspace ActiveConfiguration="Debug" />
  <MonoDevelop.Ide.ItemProperties.Assembly-CSharp PreferredExecutionTarget="970dfe81-d8aa-46bd-86d6-d540f1d2e9d8" />
  <MonoDevelop.Ide.DebuggingService.Breakpoints>
    <BreakpointStore />
  </MonoDevelop.Ide.DebuggingService.Breakpoints>
  <MultiItemStartupConfigurations />
</Properties>